PyUtilities/DidierCI.py
PyUtilities/Exceptions.py
PyUtilities/Git.py
PyUtilities/Utility.py
PyUtilities/__about__.py
PyUtilities/__init__.py
PyUtilities/py.typed
dm_py_utilities-2.1.0.dist-info/METADATA
dm_py_utilities-2.1.0.dist-info/WHEEL
dm_py_utilities-2.1.0.dist-info/entry_points.txt
dm_py_utilities-2.1.0.dist-info/licenses/LICENSE
dm_py_utilities-2.1.0.dist-info/RECORD
