Metadata-Version: 2.4
Name: dm-py-utilities
Version: 2.1.0
Summary: A utility library for my Python projects.
Project-URL: Homepage, https://code.malenfant.net/didier/PyUtilities
Project-URL: Documentation, https://code.malenfant.net/didier/PyUtilities#readme
Project-URL: Bug Tracker, https://code.malenfant.net/didier/PyUtilities/issues
Project-URL: Source Code, https://code.malenfant.net/didier/PyUtilities
Author-email: Didier Malenfant <didier@malenfant.net>
License-Expression: GPL-3.0-or-later
License-File: LICENSE
Classifier: Development Status :: 5 - Production/Stable
Classifier: Programming Language :: Python
Classifier: Programming Language :: Python :: 3.10
Classifier: Programming Language :: Python :: Implementation :: CPython
Classifier: Programming Language :: Python :: Implementation :: PyPy
Requires-Python: >=3.10
Requires-Dist: flake8
Requires-Dist: mypy
Requires-Dist: pytz
Requires-Dist: semver>=3
